{
  "indexes": [
    {
      "collectionGroup": "inventory",
      "queryScope": "COLLECTION",
      "fields": [
        {
          "fieldPath": "upce",
          "order": "ASCENDING"
        },
        {
          "fieldPath": "product_name",
          "order": "ASCENDING"
        }
      ]
    },
    {
      "collectionGroup": "payments_completed",
      "queryScope": "COLLECTION",
      "fields": [
        {
          "fieldPath": "nfc_id",
          "order": "ASCENDING"
        },
        {
          "fieldPath": "status",
          "order": "ASCENDING"
        },
        {
          "fieldPath": "timestamp",
          "order": "DESCENDING"
        }
      ]
    }
  ],
  "fieldOverrides": []
}
